sri/__init__.py
sri/autoflow/__init__.py
sri/autoflow/conditioner.py
sri/autoflow/dataset_text_reader.py
sri/autoflow/simple_column_parser.py
sri/autoflow/static_ensembler.py
sri/autoflow/var_fix.py
sri/baseline/__init__.py
sri/baseline/mean.py
sri/common/__init__.py
sri/common/config.py
sri/common/constants.py
sri/common/entrypoints.py
sri/common/util.py
sri/d3mglue/__init__.py
sri/d3mglue/d3mgrid.py
sri/d3mglue/d3mwrap.py
sri/d3mglue/pipelinecache.py
sri/interpretml/MAPLE.py
sri/interpretml/__init__.py
sri/interpretml/maple_wrap.py
sri/neural_text/__init__.py
sri/neural_text/distil_bert_text_classification.py
sri/pipelines/__init__.py
sri/pipelines/all.py
sri/pipelines/base.py
sri/pipelines/baseline_mean.py
sri/pipelines/conditioner.py
sri/pipelines/dataset_text_reader.py
sri/pipelines/datasets.py
sri/pipelines/distil_bert_text_classification.py
sri/pipelines/general_relational.py
sri/pipelines/generate_pipeline_run.py
sri/pipelines/maple.py
sri/pipelines/output_json.py
sri/pipelines/output_primitive.py
sri/pipelines/parsed_datasets.py
sri/pipelines/simple_column_parser.py
sri/pipelines/static_ensembler.py
sri/pipelines/vertex_classification.py
sri/psl/__init__.py
sri/psl/general_relational.py
sri/psl/hyperparams.py
sri/psl/psl.py
sri/psl/vertex_classification.py
sri/psl/cli/__init__.py
sri/psl/cli/general_relational_template.data
sri/psl/cli/general_relational_template.psl
sri/psl/cli/psl-cli-2.3.0-SNAPSHOT-b5698f08.jar
sri/psl/cli/vertex_classification_template.data
sri/psl/cli/vertex_classification_template.psl
sri_d3m-1.10.0.dist-info/LICENSE.txt
sri_d3m-1.10.0.dist-info/METADATA
sri_d3m-1.10.0.dist-info/NOTICE.txt
sri_d3m-1.10.0.dist-info/WHEEL
sri_d3m-1.10.0.dist-info/entry_points.txt
sri_d3m-1.10.0.dist-info/top_level.txt
sri_d3m-1.10.0.dist-info/RECORD
